param_store/__init__.py
param_store/contrib.py
param_store/interpolate.py
param_store/stores.py
param_store-0.2.2.dist-info/LICENSE
param_store-0.2.2.dist-info/METADATA
param_store-0.2.2.dist-info/WHEEL
param_store-0.2.2.dist-info/top_level.txt
param_store-0.2.2.dist-info/RECORD
